setup.cfg
setup.py
tsheets/__init__.py
tsheets/api.py
tsheets/bridge.py
tsheets/config.py
tsheets/error.py
tsheets/helpers.py
tsheets/logger.py
tsheets/model.py
tsheets/repository.py
tsheets/rest_adapter.py
tsheets/result.py
tsheets/results.py
tsheets.egg-info/PKG-INFO
tsheets.egg-info/SOURCES.txt
tsheets.egg-info/dependency_links.txt
tsheets.egg-info/pbr.json
tsheets.egg-info/requires.txt
tsheets.egg-info/top_level.txt
tsheets/models/__init__.py
tsheets/models/current_totals.py
tsheets/models/custom_field.py
tsheets/models/custom_field_item.py
tsheets/models/effective_settings.py
tsheets/models/geolocation.py
tsheets/models/jobcode.py
tsheets/models/jobcode_assignment.py
tsheets/models/last_modified_timestamps.py
tsheets/models/notification.py
tsheets/models/payroll.py
tsheets/models/project.py
tsheets/models/reminder.py
tsheets/models/timesheet.py
tsheets/models/timesheet_deleted.py
tsheets/models/user.py
tsheets/models/user_permissions_set.py
tsheets/repos/__init__.py
tsheets/repos/current_totals.py
tsheets/repos/current_user.py
tsheets/repos/custom_field_items.py
tsheets/repos/custom_fields.py
tsheets/repos/effective_settings.py
tsheets/repos/geolocations.py
tsheets/repos/jobcode_assignments.py
tsheets/repos/jobcodes.py
tsheets/repos/last_modified_timestamps.py
tsheets/repos/notifications.py
tsheets/repos/payroll.py
tsheets/repos/project.py
tsheets/repos/reminders.py
tsheets/repos/timesheets.py
tsheets/repos/timesheets_deleted.py
tsheets/repos/users.py