Metadata-Version: 1.1
Name: tsheets
Version: 0.2
Summary: API library helper for TSheets.com
Home-page: https://github.com/tsheets/api_python
Author: Kannan Ponnusamy
Author-email: kannan@endpoint.com
License: MIT
Download-URL: https://github.com/tsheets/api_python/tarball/0.1
Keywords: api,rest,tsheets
Platform: UNKNOWN
